thainlp/__init__.py
thainlp-0.4.2.dist-info/LICENSE
thainlp-0.4.2.dist-info/METADATA
thainlp-0.4.2.dist-info/WHEEL
thainlp-0.4.2.dist-info/top_level.txt
thainlp-0.4.2.dist-info/RECORD
