Metadata-Version: 2.1
Name: thainlp
Version: 0.4.2
Summary: Thai NLP library
Home-page: UNKNOWN
Author: thainlp
License: Apache Software License 2.0
Keywords: thainlp
Platform: UNKNOWN
Classifier: Development Status :: 5 - Production/Stable
Classifier: Programming Language :: Python :: 3
Classifier: Intended Audience :: Developers
Classifier: License :: OSI Approved :: Apache Software License
Classifier: Natural Language :: Thai
Classifier: Topic :: Text Processing :: Linguistic
Requires-Dist: pythainlp (>=2.0.1)
